MANIFEST.in
README.rst
VERSION
requirements.txt
setup.py
pyvoltha/__init__.py
pyvoltha.egg-info/PKG-INFO
pyvoltha.egg-info/SOURCES.txt
pyvoltha.egg-info/dependency_links.txt
pyvoltha.egg-info/requires.txt
pyvoltha.egg-info/top_level.txt
pyvoltha/adapters/__init__.py
pyvoltha/adapters/iadapter.py
pyvoltha/adapters/interface.py
pyvoltha/adapters/log_controller.py
pyvoltha/adapters/common/__init__.py
pyvoltha/adapters/common/frameio/__init__.py
pyvoltha/adapters/common/frameio/frameio.py
pyvoltha/adapters/common/frameio/third_party/__init__.py
pyvoltha/adapters/common/frameio/third_party/oftest/__init__.py
pyvoltha/adapters/common/frameio/third_party/oftest/afpacket.py
pyvoltha/adapters/common/frameio/third_party/oftest/netutils.py
pyvoltha/adapters/common/kvstore/__init__.py
pyvoltha/adapters/common/kvstore/consul_client.py
pyvoltha/adapters/common/kvstore/etcd_client.py
pyvoltha/adapters/common/kvstore/etcd_store.py
pyvoltha/adapters/common/kvstore/kv_client.py
pyvoltha/adapters/common/kvstore/kvstore.py
pyvoltha/adapters/common/kvstore/twisted_etcd_store.py
pyvoltha/adapters/common/pon_resource_manager/__init__.py
pyvoltha/adapters/common/pon_resource_manager/resource_kv_store.py
pyvoltha/adapters/common/pon_resource_manager/resource_manager.py
pyvoltha/adapters/extensions/__init__.py
pyvoltha/adapters/extensions/events/__init__.py
pyvoltha/adapters/extensions/events/adapter_events.py
pyvoltha/adapters/extensions/events/device_events/__init__.py
pyvoltha/adapters/extensions/events/device_events/heartbeat_event.py
pyvoltha/adapters/extensions/events/device_events/olt/__init__.py
pyvoltha/adapters/extensions/events/device_events/olt/olt_los_alarm.py
pyvoltha/adapters/extensions/events/device_events/onu/__init__.py
pyvoltha/adapters/extensions/events/device_events/onu/onu_activation_fail_event.py
pyvoltha/adapters/extensions/events/device_events/onu/onu_active_event.py
pyvoltha/adapters/extensions/events/device_events/onu/onu_deleted_event.py
pyvoltha/adapters/extensions/events/device_events/onu/onu_disabled_event.py
pyvoltha/adapters/extensions/events/device_events/onu/onu_discovery_event.py
