Metadata-Version: 1.1
Name: pyvoltha
Version: 2.5.7
Summary: VOLTHA Python support libraries
Home-page: https://wiki.opencord.org/display/CORD/VOLTHA
Author: Chip Boling
Author-email: chip@bcsw.net
License: UNKNOWN
Platform: UNKNOWN
Classifier: Development Status :: 3 - Alpha
Classifier: Intended Audience :: Developers
Classifier: Topic :: Software Development :: Libraries
Classifier: License :: OSI Approved :: Apache Software License
Classifier: Programming Language :: Python :: 2
Classifier: Programming Language :: Python :: 2.7
Classifier: Programming Language :: Python :: 3.5
Classifier: Programming Language :: Python :: 3.6
Classifier: Programming Language :: Python :: 3.7
